pulsar_paragraph/data_files/pulsars-links_available.csv
pulsar_paragraph/load_data.py
pulsar_paragraph/pulsar_classes.py
pulsar_paragraph/pulsar_paragraph.py
pulsar_paragraph-1.0.2.dist-info/LICENSE
pulsar_paragraph-1.0.2.dist-info/METADATA
pulsar_paragraph-1.0.2.dist-info/WHEEL
pulsar_paragraph-1.0.2.dist-info/entry_points.txt
pulsar_paragraph-1.0.2.dist-info/RECORD
