Metadata-Version: 2.1
Name: pulsar-paragraph
Version: 1.0.2
Summary: A python package that can create a human readable summary of a pulsar based on information for the ANTF pulsar catalogue
License: MIT
Author: NickSwainston
Author-email: nickaswainston@gmail.com
Requires-Python: >=3.8,<4.0
Classifier: License :: OSI Approved :: MIT License
Classifier: Programming Language :: Python :: 3
Classifier: Programming Language :: Python :: 3.8
Classifier: Programming Language :: Python :: 3.9
Classifier: Programming Language :: Python :: 3.10
Classifier: Programming Language :: Python :: 3.11
Requires-Dist: pandas (>=1.4.2,<2.0.0)
Requires-Dist: psrqpy (>=1.2.7,<2.0.0)
